WoYeYouhuayaoshuoPutongrenDeDangzhongJianghuaJineng/README.md
WoYeYouhuayaoshuoPutongrenDeDangzhongJianghuaJineng/__init__.py
WoYeYouhuayaoshuoPutongrenDeDangzhongJianghuaJineng/__main__.py
WoYeYouhuayaoshuoPutongrenDeDangzhongJianghuaJineng/file.epub
WoYeYouhuayaoshuoPutongrenDeDangzhongJianghuaJineng/index.html
WoYeYouhuayaoshuoPutongrenDeDangzhongJianghuaJineng/css/__init__.py
WoYeYouhuayaoshuoPutongrenDeDangzhongJianghuaJineng/css/annotations.css
WoYeYouhuayaoshuoPutongrenDeDangzhongJianghuaJineng/css/main.css
WoYeYouhuayaoshuoPutongrenDeDangzhongJianghuaJineng/css/normalize.css
WoYeYouhuayaoshuoPutongrenDeDangzhongJianghuaJineng/css/popup.css
WoYeYouhuayaoshuoPutongrenDeDangzhongJianghuaJineng/font/__init__.py
WoYeYouhuayaoshuoPutongrenDeDangzhongJianghuaJineng/font/fontello.eot
WoYeYouhuayaoshuoPutongrenDeDangzhongJianghuaJineng/font/fontello.svg
WoYeYouhuayaoshuoPutongrenDeDangzhongJianghuaJineng/font/fontello.ttf
WoYeYouhuayaoshuoPutongrenDeDangzhongJianghuaJineng/font/fontello.woff
WoYeYouhuayaoshuoPutongrenDeDangzhongJianghuaJineng/img/__init__.py
WoYeYouhuayaoshuoPutongrenDeDangzhongJianghuaJineng/img/annotator-glyph-sprite.png
WoYeYouhuayaoshuoPutongrenDeDangzhongJianghuaJineng/img/annotator-icon-sprite.png
WoYeYouhuayaoshuoPutongrenDeDangzhongJianghuaJineng/img/apple-touch-icon.png
WoYeYouhuayaoshuoPutongrenDeDangzhongJianghuaJineng/img/cancelfullscreen.png
WoYeYouhuayaoshuoPutongrenDeDangzhongJianghuaJineng/img/close.png
WoYeYouhuayaoshuoPutongrenDeDangzhongJianghuaJineng/img/fullscreen.png
WoYeYouhuayaoshuoPutongrenDeDangzhongJianghuaJineng/img/loader.gif
WoYeYouhuayaoshuoPutongrenDeDangzhongJianghuaJineng/img/menu-icon.png
WoYeYouhuayaoshuoPutongrenDeDangzhongJianghuaJineng/img/save.png
WoYeYouhuayaoshuoPutongrenDeDangzhongJianghuaJineng/img/saved.png
WoYeYouhuayaoshuoPutongrenDeDangzhongJianghuaJineng/img/settings-s.png
WoYeYouhuayaoshuoPutongrenDeDangzhongJianghuaJineng/img/settings.png
wo_ye_youhuayaoshuo_putongren_de_dangzhong_jianghua_jineng-2024.3.5.0.dist-info/METADATA
wo_ye_youhuayaoshuo_putongren_de_dangzhong_jianghua_jineng-2024.3.5.0.dist-info/WHEEL
wo_ye_youhuayaoshuo_putongren_de_dangzhong_jianghua_jineng-2024.3.5.0.dist-info/entry_points.txt
wo_ye_youhuayaoshuo_putongren_de_dangzhong_jianghua_jineng-2024.3.5.0.dist-info/top_level.txt
wo_ye_youhuayaoshuo_putongren_de_dangzhong_jianghua_jineng-2024.3.5.0.dist-info/RECORD
